aio_telegram_client/__init__.py
aio_telegram_client-0.1.0a0.dist-info/LICENSE
aio_telegram_client-0.1.0a0.dist-info/WHEEL
aio_telegram_client-0.1.0a0.dist-info/METADATA
aio_telegram_client-0.1.0a0.dist-info/RECORD
