Metadata-Version: 2.1
Name: aio-telegram-client
Version: 0.1.0a0
Summary: Python aiohttp telegram client 
Home-page: https://github.com/skar404/aio-clients
License: MIT
Author: Denis Malin
Author-email: denis@malina.page
Requires-Python: >=3.10,<4.0
Classifier: License :: OSI Approved :: MIT License
Classifier: Programming Language :: Python :: 3
Classifier: Programming Language :: Python :: 3.10
Requires-Dist: aio-clients (>=0.1.0-alpha.2)
Project-URL: Documentation, https://github.com/skar404/aio-clients
Project-URL: Repository, https://github.com/skar404/aio-clients
